certomancer_csc_dummy-0.4.2.dist-info/licenses/LICENSE
csc_dummy/__init__.py
csc_dummy/__main__.py
csc_dummy/csc_dummy_server.py
csc_dummy/runner.py
csc_dummy/version.py
certomancer_csc_dummy-0.4.2.dist-info/METADATA
certomancer_csc_dummy-0.4.2.dist-info/WHEEL
certomancer_csc_dummy-0.4.2.dist-info/entry_points.txt
certomancer_csc_dummy-0.4.2.dist-info/top_level.txt
certomancer_csc_dummy-0.4.2.dist-info/RECORD
