Metadata-Version: 2.4
Name: certomancer-csc-dummy
Version: 0.4.2
Summary: A Certomancer-based demo CSC server for integration tests
Home-page: https://github.com/MatthiasValvekens/certomancer-csc-dummy
Author: Matthias Valvekens
Author-email: dev@mvalvekens.be
License: MIT
Keywords: pki testing csc signature
Classifier: Development Status :: 3 - Alpha
Classifier: Intended Audience :: Developers
Classifier: License :: OSI Approved :: MIT License
Classifier: Programming Language :: Python :: 3
Classifier: Programming Language :: Python :: 3.9
Classifier: Programming Language :: Python :: 3.10
Classifier: Programming Language :: Python :: 3.11
Classifier: Programming Language :: Python :: 3.12
Classifier: Programming Language :: Python :: 3.13
Classifier: Topic :: Security :: Cryptography
Classifier: Topic :: Software Development :: Libraries :: Python Modules
License-File: LICENSE
Requires-Dist: asn1crypto>=1.5.0
Requires-Dist: cryptography>=3.3.1
Requires-Dist: certomancer>=0.13.0
Requires-Dist: aiohttp>=3.9.0
Requires-Dist: python-pae==0.1.0
Dynamic: author
Dynamic: author-email
Dynamic: classifier
Dynamic: description
Dynamic: description-content-type
Dynamic: home-page
Dynamic: keywords
Dynamic: license
Dynamic: license-file
Dynamic: requires-dist
Dynamic: summary
